z3_rideshare_planner/__init__.py
z3_rideshare_planner/carshare.py
z3_rideshare_planner/rideshare_planner.py
z3_rideshare_planner-0.4.6.dist-info/LICENSE
z3_rideshare_planner-0.4.6.dist-info/METADATA
z3_rideshare_planner-0.4.6.dist-info/WHEEL
z3_rideshare_planner-0.4.6.dist-info/top_level.txt
z3_rideshare_planner-0.4.6.dist-info/RECORD
